UART_RX.v
// ============================================================
// UART Receiver
// Samples at the MIDDLE of each bit using 16x oversampling.
// os_tick: a single-cycle pulse at 16x the baud rate.
// Includes a 2-FF synchronizer on the raw RX pin.
// ============================================================
module uart_rx (
    input  wire       clk,
    input  wire       rst,
    input  wire        os_tick,     // 16x baud-rate tick
    input  wire        rx_raw,      // asynchronous serial input pin
    output reg  [7:0]  rx_data,
    output reg          rx_valid    // 1-cycle pulse when a byte is ready
);

    // ---- 2-FF synchronizer: brings async rx_raw into our clock domain ----
    reg rx_sync0, rx_sync1;
    always @(posedge clk) begin
        rx_sync0 <= rx_raw;
        rx_sync1 <= rx_sync0;
    end
    wire rx = rx_sync1;

    localparam IDLE  = 2'b00;
    localparam START = 2'b01;
    localparam DATA  = 2'b10;
    localparam STOP  = 2'b11;

    reg [1:0] state;
    reg [3:0] os_count;   // 0-15 counter within one bit period
    reg [2:0] bit_idx;    // which data bit (0-7)
    reg [7:0] shift_reg;

    always @(posedge clk) begin
        if (rst) begin
            state    <= IDLE;
            rx_valid <= 1'b0;
            os_count <= 4'd0;
            bit_idx  <= 3'd0;
        end else begin
            rx_valid <= 1'b0;   // default: pulse only for one cycle

            case (state)
                // Wait for the line to fall (start bit begins)
                IDLE: begin
                    if (!rx) begin
                        os_count <= 4'd0;
                        state    <= START;
                    end
                end

                // Confirm start bit at the MIDDLE of the bit period (count=7)
                // to reject glitches, then move to DATA
                START: if (os_tick) begin
                    if (os_count == 4'd7) begin
                        if (!rx) begin        // still low -> valid start bit
                            os_count <= 4'd0;
                            bit_idx  <= 3'd0;
                            state    <= DATA;
                        end else begin        // was a glitch, go back
                            state <= IDLE;
                        end
                    end else begin
                        os_count <= os_count + 1;
                    end
                end

                // Sample each data bit at its middle (count=15, i.e. 16 ticks later)
                DATA: if (os_tick) begin
                    if (os_count == 4'd15) begin
                        os_count <= 4'd0;
                        shift_reg <= {rx, shift_reg[7:1]};  // shift MSB<-rx, LSB first order
                        if (bit_idx == 3'd7)
                            state <= STOP;
                        else
                            bit_idx <= bit_idx + 1;
                    end else begin
                        os_count <= os_count + 1;
                    end
                end

                // Sample stop bit at its middle, then output the byte
                STOP: if (os_tick) begin
                    if (os_count == 4'd15) begin
                        rx_data  <= shift_reg;
                        rx_valid <= rx;   // only flag valid if stop bit is 1 (framing check)
                        state    <= IDLE;
                    end else begin
                        os_count <= os_count + 1;
                    end
                end

                default: state <= IDLE;
            endcase
        end
    end

endmodule

UART_TX.v
// ============================================================
// UART Transmitter
// 8 data bits, 1 start bit, 1 stop bit, no parity
// baud_tick: a single-cycle pulse generated at the baud rate
//            (feed it from a baud rate generator / clock divider)
// ============================================================
module uart_tx (
    input  wire       clk,
    input  wire       rst,
    input  wire        baud_tick,   // 1-cycle pulse at bit rate
    input  wire        tx_start,    // pulse to begin transmission
    input  wire [7:0]  tx_data,
    output reg          tx,         // serial line (idle = 1)
    output reg          tx_busy
);

    localparam IDLE  = 2'b00;
    localparam START = 2'b01;
    localparam DATA  = 2'b10;
    localparam STOP  = 2'b11;

    reg [1:0] state;
    reg [2:0] bit_idx;      // counts 0-7 for the 8 data bits
    reg [7:0] shift_reg;

    always @(posedge clk) begin
        if (rst) begin
            state    <= IDLE;
            tx       <= 1'b1;   // idle line is HIGH
            tx_busy  <= 1'b0;
            bit_idx  <= 3'd0;
        end else begin
            case (state)
                IDLE: begin
                    tx <= 1'b1;
                    if (tx_start) begin
                        shift_reg <= tx_data;
                        tx_busy   <= 1'b1;
                        state     <= START;
                    end
                end

                START: if (baud_tick) begin
                    tx      <= 1'b0;      // start bit = 0
                    bit_idx <= 3'd0;
                    state   <= DATA;
                end

                DATA: if (baud_tick) begin
                    tx        <= shift_reg[0];
                    shift_reg <= shift_reg >> 1;
                    if (bit_idx == 3'd7)
                        state <= STOP;
                    else
                        bit_idx <= bit_idx + 1;
                end

                STOP: if (baud_tick) begin
                    tx      <= 1'b1;      // stop bit = 1
                    tx_busy <= 1'b0;
                    state   <= IDLE;
                end

                default: state <= IDLE;
            endcase
        end
    end

endmodule

loopback.v
`timescale 1ns/1ps
 
module uart_loopback_tb;
 
    reg clk, rst;
    reg tx_start;
    reg [7:0] tx_data;
    wire tx_serial, tx_busy;
    wire [7:0] rx_data;
    wire rx_valid;
 
    reg baud_tick, os_tick;
    integer baud_div_count, os_div_count;
 
    // ---- Clock: 100MHz (10ns period) ----
    always #5 clk = ~clk;
 
    // ---- baud_tick every 64 clk cycles, os_tick every 4 clk cycles ----
    // (64 = 16 * 4, so os_tick fires exactly 16x per baud period)
    always @(posedge clk) begin
        if (rst) begin
            baud_div_count <= 0;
            os_div_count   <= 0;
            baud_tick      <= 0;
            os_tick        <= 0;
        end else begin
            baud_div_count <= (baud_div_count == 63) ? 0 : baud_div_count + 1;
            baud_tick      <= (baud_div_count == 63);
 
            os_div_count   <= (os_div_count == 3) ? 0 : os_div_count + 1;
            os_tick        <= (os_div_count == 3);
        end
    end
 
    uart_tx dut_tx (
        .clk(clk), .rst(rst),
        .baud_tick(baud_tick),
        .tx_start(tx_start),
        .tx_data(tx_data),
        .tx(tx_serial),
        .tx_busy(tx_busy)
    );
 
    uart_rx dut_rx (
        .clk(clk), .rst(rst),
        .os_tick(os_tick),
        .rx_raw(tx_serial),     // direct loopback, no external noise
        .rx_data(rx_data),
        .rx_valid(rx_valid)
    );
 
    integer errors;
 
    task send_byte(input [7:0] b);
        begin
            @(posedge clk);
            tx_data  = b;
            tx_start = 1;
            @(posedge clk);
            tx_start = 0;
            // wait for TX to finish this byte
            wait (tx_busy == 0);
        end
    endtask

    initial begin

        $dumpfile("wave.vcd");
        $dumpvars(0, uart_loopback_tb);


        clk = 0; rst = 1; tx_start = 0; tx_data = 8'h00;
        errors = 0;
        repeat (5) @(posedge clk);
        rst = 0;
 
        send_byte(8'hA5);
        wait (rx_valid == 1);
        @(posedge clk);
        if (rx_data !== 8'hA5) begin
            $display("FAIL: expected A5, got %h", rx_data);
            errors = errors + 1;
        end else
            $display("PASS: byte A5 received correctly");
 
        send_byte(8'h3C);
        wait (rx_valid == 1);
        @(posedge clk);
        if (rx_data !== 8'h3C) begin
            $display("FAIL: expected 3C, got %h", rx_data);
            errors = errors + 1;
        end else
            $display("PASS: byte 3C received correctly");
 
        send_byte(8'h00);
        wait (rx_valid == 1);
        @(posedge clk);
        if (rx_data !== 8'h00) begin
            $display("FAIL: expected 00, got %h", rx_data);
            errors = errors + 1;
        end else
            $display("PASS: byte 00 received correctly");
 
        send_byte(8'hFF);
        wait (rx_valid == 1);
        @(posedge clk);
        if (rx_data !== 8'hFF) begin
            $display("FAIL: expected FF, got %h", rx_data);
            errors = errors + 1;
        end else
            $display("PASS: byte FF received correctly");
 
        if (errors == 0)
            $display("ALL TESTS PASSED");
        else
            $display("%0d TEST(S) FAILED", errors);
 
        $finish;
    end
 
endmodule

wave.vcd
$date
	Fri Sep 25 11:22:18 2026
$end
$version
	Icarus Verilog
$end
$timescale
	1ps
$end
$scope module uart_loopback_tb $end
$var wire 1 ! tx_serial $end
$var wire 1 " tx_busy $end
$var wire 1 # rx_valid $end
$var wire 8 $ rx_data [7:0] $end
$var reg 1 % baud_tick $end
$var reg 1 & clk $end
$var reg 1 ' os_tick $end
$var reg 1 ( rst $end
$var reg 8 ) tx_data [7:0] $end
$var reg 1 * tx_start $end
$var integer 32 + baud_div_count [31:0] $end
$var integer 32 , errors [31:0] $end
$var integer 32 - os_div_count [31:0] $end
$scope module dut_rx $end
$var wire 1 & clk $end
$var wire 1 ' os_tick $end
$var wire 1 ( rst $end
$var wire 1 . rx $end
$var wire 1 ! rx_raw $end
$var parameter 2 / DATA $end
$var parameter 2 0 IDLE $end
$var parameter 2 1 START $end
$var parameter 2 2 STOP $end
$var reg 3 3 bit_idx [2:0] $end
$var reg 4 4 os_count [3:0] $end
$var reg 8 5 rx_data [7:0] $end
$var reg 1 6 rx_sync0 $end
$var reg 1 7 rx_sync1 $end
$var reg 1 # rx_valid $end
$var reg 8 8 shift_reg [7:0] $end
$var reg 2 9 state [1:0] $end
$upscope $end
$scope module dut_tx $end
$var wire 1 % baud_tick $end
$var wire 1 & clk $end
$var wire 1 ( rst $end
$var wire 8 : tx_data [7:0] $end
$var wire 1 * tx_start $end
$var parameter 2 ; DATA $end
$var parameter 2 < IDLE $end
$var parameter 2 = START $end
$var parameter 2 > STOP $end
$var reg 3 ? bit_idx [2:0] $end
$var reg 8 @ shift_reg [7:0] $end
$var reg 2 A state [1:0] $end
$var reg 1 ! tx $end
$var reg 1 " tx_busy $end
$upscope $end
$scope task send_byte $end
$var reg 8 B b [7:0] $end
$upscope $end
$upscope $end
$enddefinitions $end
$comment Show the parameter values. $end
$dumpall
b11 >
b1 =
b0 <
b10 ;
b11 2
b1 1
b0 0
b10 /
$end
#0
$dumpvars
bx B
bx A
bx @
bx ?
b0 :
bx 9
bx 8
x7
x6
bx 5
bx 4
bx 3
x.
bx -
b0 ,
bx +
0*
b0 )
1(
x'
0&
x%
bx $
x#
x"
x!
$end
#5000
b0 ?
0"
1!
b0 A
b0 3
b0 4
0#
b0 9
0'
0%
b0 -
b0 +
1&
#10000
0&
#15000
16
1&
#20000
0&
#25000
1.
17
1&
#30000
0&
#35000
1&
#40000
0&
#45000
b1 -
b1 +
b10100101 B
0(
1&
#50000
0&
#55000
b10 -
b10 +
b1 A
1"
b10100101 @
1*
b10100101 )
b10100101 :
1&
#60000
0&
#65000
b11 -
b11 +
0*
1&
#70000
0&
#75000
1'
b0 -
b100 +
1&
#80000
0&
#85000
0'
b1 -
b101 +
1&
#90000
0&
#95000
b10 -
b110 +
1&
#100000
0&
#105000
b11 -
b111 +
1&
#110000
0&
#115000
1'
b0 -
b1000 +
1&
#120000
0&
#125000
0'
b1 -
b1001 +
1&
#130000
0&
#135000
b10 -
b1010 +
1&
#140000
0&
#145000
b11 -
b1011 +
1&
#150000
0&
#155000
1'
b0 -
b1100 +
1&
#160000
0&
#165000
0'
b1 -
b1101 +
1&
#170000
0&
#175000
b10 -
b1110 +
1&
#180000
0&
#185000
b11 -
b1111 +
1&
#190000
0&
#195000
1'
b0 -
b10000 +
1&
#200000
0&
#205000
0'
b1 -
b10001 +
1&
#210000
0&
#215000
b10 -
b10010 +
1&
#220000
0&
#225000
b11 -
b10011 +
1&
#230000
0&
#235000
1'
b0 -
b10100 +
1&
#240000
0&
#245000
0'
b1 -
b10101 +
1&
#250000
0&
#255000
b10 -
b10110 +
1&
#260000
0&
#265000
b11 -
b10111 +
1&
#270000
0&
#275000
1'
b0 -
b11000 +
1&
#280000
0&
#285000
0'
b1 -
b11001 +
1&
#290000
0&
#295000
b10 -
b11010 +
1&
#300000
0&
#305000
b11 -
b11011 +
1&
#310000
0&
#315000
1'
b0 -
b11100 +
1&
#320000
0&
#325000
0'
b1 -
b11101 +
1&
#330000
0&
#335000
b10 -
b11110 +
1&
#340000
0&
#345000
b11 -
b11111 +
1&
#350000
0&
#355000
1'
b0 -
b100000 +
1&
#360000
0&
#365000
0'
b1 -
b100001 +
1&
#370000
0&
#375000
b10 -
b100010 +
1&
#380000
0&
#385000
b11 -
b100011 +
1&
#390000
0&
#395000
1'
b0 -
b100100 +
1&
#400000
0&
#405000
0'
b1 -
b100101 +
1&
#410000
0&
#415000
b10 -
b100110 +
1&
#420000
0&
#425000
b11 -
b100111 +
1&
#430000
0&
#435000
1'
b0 -
b101000 +
1&
#440000
0&
#445000
0'
b1 -
b101001 +
1&
#450000
0&
#455000
b10 -
b101010 +
1&
#460000
0&
#465000
b11 -
b101011 +
1&
#470000
0&
#475000
1'
b0 -
b101100 +
1&
#480000
0&
#485000
0'
b1 -
b101101 +
1&
#490000
0&
#495000
b10 -
b101110 +
1&
#500000
0&
#505000
b11 -
b101111 +
1&
#510000
0&
#515000
1'
b0 -
b110000 +
1&
#520000
0&
#525000
0'
b1 -
b110001 +
1&
#530000
0&
#535000
b10 -
b110010 +
1&
#540000
0&
#545000
b11 -
b110011 +
1&
#550000
0&
#555000
1'
b0 -
b110100 +
1&
#560000
0&
#565000
0'
b1 -
b110101 +
1&
#570000
0&
#575000
b10 -
b110110 +
1&
#580000
0&
#585000
b11 -
b110111 +
1&
#590000
0&
#595000
1'
b0 -
b111000 +
1&
#600000
0&
#605000
0'
b1 -
b111001 +
1&
#610000
0&
#615000
b10 -
b111010 +
1&
#620000
0&
#625000
b11 -
b111011 +
1&
#630000
0&
#635000
1'
b0 -
b111100 +
1&
#640000
0&
#645000
0'
b1 -
b111101 +
1&
#650000
0&
#655000
b10 -
b111110 +
1&
#660000
0&
#665000
b11 -
b111111 +
1&
#670000
0&
#675000
1'
b0 -
1%
b0 +
1&
#680000
0&
#685000
b10 A
0!
0'
b1 -
0%
b1 +
1&
#690000
0&
#695000
b10 -
b10 +
06
1&
#700000
0&
#705000
0.
07
b11 -
b11 +
1&
#710000
0&
#715000
1'
b0 -
b100 +
b1 9
1&
#720000
0&
#725000
b1 4
0'
b1 -
b101 +
1&
#730000
0&
#735000
b10 -
b110 +
1&
#740000
0&
#745000
b11 -
b111 +
1&
#750000
0&
#755000
1'
b0 -
b1000 +
1&
#760000
0&
#765000
b10 4
0'
b1 -
b1001 +
1&
#770000
0&
#775000
b10 -
b1010 +
1&
#780000
0&
#785000
b11 -
b1011 +
1&
#790000
0&
#795000
1'
b0 -
b1100 +
1&
#800000
0&
#805000
b11 4
0'
b1 -
b1101 +
1&
#810000
0&
#815000
b10 -
b1110 +
1&
#820000
0&
#825000
b11 -
b1111 +
1&
#830000
0&
#835000
1'
b0 -
b10000 +
1&
#840000
0&
#845000
b100 4
0'
b1 -
b10001 +
1&
#850000
0&
#855000
b10 -
b10010 +
1&
#860000
0&
#865000
b11 -
b10011 +
1&
#870000
0&
#875000
1'
b0 -
b10100 +
1&
#880000
0&
#885000
b101 4
0'
b1 -
b10101 +
1&
#890000
0&
#895000
b10 -
b10110 +
1&
#900000
0&
#905000
b11 -
b10111 +
1&
#910000
0&
#915000
1'
b0 -
b11000 +
1&
#920000
0&
#925000
b110 4
0'
b1 -
b11001 +
1&
#930000
0&
#935000
b10 -
b11010 +
1&
#940000
0&
#945000
b11 -
b11011 +
1&
#950000
0&
#955000
1'
b0 -
b11100 +
1&
#960000
0&
#965000
b111 4
0'
b1 -
b11101 +
1&
#970000
0&
#975000
b10 -
b11110 +
1&
#980000
0&
#985000
b11 -
b11111 +
1&
#990000
0&
#995000
1'
b0 -
b100000 +
1&
#1000000
0&
#1005000
b10 9
b0 4
0'
b1 -
b100001 +
1&
#1010000
0&
#1015000
b10 -
b100010 +
1&
#1020000
0&
#1025000
b11 -
b100011 +
1&
#1030000
0&
#1035000
1'
b0 -
b100100 +
1&
#1040000
0&
#1045000
b1 4
0'
b1 -
b100101 +
1&
#1050000
0&
#1055000
b10 -
b100110 +
1&
#1060000
0&
#1065000
b11 -
b100111 +
1&
#1070000
0&
#1075000
1'
b0 -
b101000 +
1&
#1080000
0&
#1085000
b10 4
0'
b1 -
b101001 +
1&
#1090000
0&
#1095000
b10 -
b101010 +
1&
#1100000
0&
#1105000
b11 -
b101011 +
1&
#1110000
0&
#1115000
1'
b0 -
b101100 +
1&
#1120000
0&
#1125000
b11 4
0'
b1 -
b101101 +
1&
#1130000
0&
#1135000
b10 -
b101110 +
1&
#1140000
0&
#1145000
b11 -
b101111 +
1&
#1150000
0&
#1155000
1'
b0 -
b110000 +
1&
#1160000
0&
#1165000
b100 4
0'
b1 -
b110001 +
1&
#1170000
0&
#1175000
b10 -
b110010 +
1&
#1180000
0&
#1185000
b11 -
b110011 +
1&
#1190000
0&
#1195000
1'
b0 -
b110100 +
1&
#1200000
0&
#1205000
b101 4
0'
b1 -
b110101 +
1&
#1210000
0&
#1215000
b10 -
b110110 +
1&
#1220000
0&
#1225000
b11 -
b110111 +
1&
#1230000
0&
#1235000
1'
b0 -
b111000 +
1&
#1240000
0&
#1245000
b110 4
0'
b1 -
b111001 +
1&
#1250000
0&
#1255000
b10 -
b111010 +
1&
#1260000
0&
#1265000
b11 -
b111011 +
1&
#1270000
0&
#1275000
1'
b0 -
b111100 +
1&
#1280000
0&
#1285000
b111 4
0'
b1 -
b111101 +
1&
#1290000
0&
#1295000
b10 -
b111110 +
1&
#1300000
0&
#1305000
b11 -
b111111 +
1&
#1310000
0&
#1315000
1'
b0 -
1%
b0 +
1&
#1320000
0&
#1325000
b1 ?
b1010010 @
1!
b1000 4
0'
b1 -
0%
b1 +
1&
#1330000
0&
#1335000
b10 -
b10 +
16
1&
#1340000
0&
#1345000
1.
17
b11 -
b11 +
1&
#1350000
0&
#1355000
1'
b0 -
b100 +
1&
#1360000
0&
#1365000
b1001 4
0'
b1 -
b101 +
1&
#1370000
0&
#1375000
b10 -
b110 +
1&
#1380000
0&
#1385000
b11 -
b111 +
1&
#1390000
0&
#1395000
1'
b0 -
b1000 +
1&
#1400000
0&
#1405000
b1010 4
0'
b1 -
b1001 +
1&
#1410000
0&
#1415000
b10 -
b1010 +
1&
#1420000
0&
#1425000
b11 -
b1011 +
1&
#1430000
0&
#1435000
1'
b0 -
b1100 +
1&
#1440000
0&
#1445000
b1011 4
0'
b1 -
b1101 +
1&
#1450000
0&
#1455000
b10 -
b1110 +
1&
#1460000
0&
#1465000
b11 -
b1111 +
1&
#1470000
0&
#1475000
1'
b0 -
b10000 +
1&
#1480000
0&
#1485000
b1100 4
0'
b1 -
b10001 +
1&
#1490000
0&
#1495000
b10 -
b10010 +
1&
#1500000
0&
#1505000
b11 -
b10011 +
1&
#1510000
0&
#1515000
1'
b0 -
b10100 +
1&
#1520000
0&
#1525000
b1101 4
0'
b1 -
b10101 +
1&
#1530000
0&
#1535000
b10 -
b10110 +
1&
#1540000
0&
#1545000
b11 -
b10111 +
1&
#1550000
0&
#1555000
1'
b0 -
b11000 +
1&
#1560000
0&
#1565000
b1110 4
0'
b1 -
b11001 +
1&
#1570000
0&
#1575000
b10 -
b11010 +
1&
#1580000
0&
#1585000
b11 -
b11011 +
1&
#1590000
0&
#1595000
1'
b0 -
b11100 +
1&
#1600000
0&
#1605000
b1111 4
0'
b1 -
b11101 +
1&
#1610000
0&
#1615000
b10 -
b11110 +
1&
#1620000
0&
#1625000
b11 -
b11111 +
1&
#1630000
0&
#1635000
1'
b0 -
b100000 +
1&
#1640000
0&
#1645000
b1 3
b1xxxxxxx 8
b0 4
0'
b1 -
b100001 +
1&
#1650000
0&
#1655000
b10 -
b100010 +
1&
#1660000
0&
#1665000
b11 -
b100011 +
1&
#1670000
0&
#1675000
1'
b0 -
b100100 +
1&
#1680000
0&
#1685000
b1 4
0'
b1 -
b100101 +
1&
#1690000
0&
#1695000
b10 -
b100110 +
1&
#1700000
0&
#1705000
b11 -
b100111 +
1&
#1710000
0&
#1715000
1'
b0 -
b101000 +
1&
#1720000
0&
#1725000
b10 4
0'
b1 -
b101001 +
1&
#1730000
0&
#1735000
b10 -
b101010 +
1&
#1740000
0&
#1745000
b11 -
b101011 +
1&
#1750000
0&
#1755000
1'
b0 -
b101100 +
1&
#1760000
0&
#1765000
b11 4
0'
b1 -
b101101 +
1&
#1770000
0&
#1775000
b10 -
b101110 +
1&
#1780000
0&
#1785000
b11 -
b101111 +
1&
#1790000
0&
#1795000
1'
b0 -
b110000 +
1&
#1800000
0&
#1805000
b100 4
0'
b1 -
b110001 +
1&
#1810000
0&
#1815000
b10 -
b110010 +
1&
#1820000
0&
#1825000
b11 -
b110011 +
1&
#1830000
0&
#1835000
1'
b0 -
b110100 +
1&
#1840000
0&
#1845000
b101 4
0'
b1 -
b110101 +
1&
#1850000
0&
#1855000
b10 -
b110110 +
1&
#1860000
0&
#1865000
b11 -
b110111 +
1&
#1870000
0&
#1875000
1'
b0 -
b111000 +
1&
#1880000
0&
#1885000
b110 4
0'
b1 -
b111001 +
1&
#1890000
0&
#1895000
b10 -
b111010 +
1&
#1900000
0&
#1905000
b11 -
b111011 +
1&
#1910000
0&
#1915000
1'
b0 -
b111100 +
1&
#1920000
0&
#1925000
b111 4
0'
b1 -
b111101 +
1&
#1930000
0&
#1935000
b10 -
b111110 +
1&
#1940000
0&
#1945000
b11 -
b111111 +
1&
#1950000
0&
#1955000
1'
b0 -
1%
b0 +
1&
#1960000
0&
#1965000
b10 ?
b101001 @
0!
b1000 4
0'
b1 -
0%
b1 +
1&
#1970000
0&
#1975000
b10 -
b10 +
06
1&
#1980000
0&
#1985000
0.
07
b11 -
b11 +
1&
#1990000
0&
#1995000
1'
b0 -
b100 +
1&
#2000000
0&
#2005000
b1001 4
0'
b1 -
b101 +
1&
#2010000
0&
#2015000
b10 -
b110 +
1&
#2020000
0&
#2025000
b11 -
b111 +
1&
#2030000
0&
#2035000
1'
b0 -
b1000 +
1&
#2040000
0&
#2045000
b1010 4
0'
b1 -
b1001 +
1&
#2050000
0&
#2055000
b10 -
b1010 +
1&
#2060000
0&
#2065000
b11 -
b1011 +
1&
#2070000
0&
#2075000
1'
b0 -
b1100 +
1&
#2080000
0&
#2085000
b1011 4
0'
b1 -
b1101 +
1&
#2090000
0&
#2095000
b10 -
b1110 +
1&
#2100000
0&
#2105000
b11 -
b1111 +
1&
#2110000
0&
#2115000
1'
b0 -
b10000 +
1&
#2120000
0&
#2125000
b1100 4
0'
b1 -
b10001 +
1&
#2130000
0&
#2135000
b10 -
b10010 +
1&
#2140000
0&
#2145000
b11 -
b10011 +
1&
#2150000
0&
#2155000
1'
b0 -
b10100 +
1&
#2160000
0&
#2165000
b1101 4
0'
b1 -
b10101 +
1&
#2170000
0&
#2175000
b10 -
b10110 +
1&
#2180000
0&
#2185000
b11 -
b10111 +
1&
#2190000
0&
#2195000
1'
b0 -
b11000 +
1&
#2200000
0&
#2205000
b1110 4
0'
b1 -
b11001 +
1&
#2210000
0&
#2215000
b10 -
b11010 +
1&
#2220000
0&
#2225000
b11 -
b11011 +
1&
#2230000
0&
#2235000
1'
b0 -
b11100 +
1&
#2240000
0&
#2245000
b1111 4
0'
b1 -
b11101 +
1&
#2250000
0&
#2255000
b10 -
b11110 +
1&
#2260000
0&
#2265000
b11 -
b11111 +
1&
#2270000
0&
#2275000
1'
b0 -
b100000 +
1&
#2280000
0&
#2285000
b10 3
b1xxxxxx 8
b0 4
0'
b1 -
b100001 +
1&
#2290000
0&
#2295000
b10 -
b100010 +
1&
#2300000
0&
#2305000
b11 -
b100011 +
1&
#2310000
0&
#2315000
1'
b0 -
b100100 +
1&
#2320000
0&
#2325000
b1 4
0'
b1 -
b100101 +
1&
#2330000
0&
#2335000
b10 -
b100110 +
1&
#2340000
0&
#2345000
b11 -
b100111 +
1&
#2350000
0&
#2355000
1'
b0 -
b101000 +
1&
#2360000
0&
#2365000
b10 4
0'
b1 -
b101001 +
1&
#2370000
0&
#2375000
b10 -
b101010 +
1&
#2380000
0&
#2385000
b11 -
b101011 +
1&
#2390000
0&
#2395000
1'
b0 -
b101100 +
1&
#2400000
0&
#2405000
b11 4
0'
b1 -
b101101 +
1&
#2410000
0&
#2415000
b10 -
b101110 +
1&
#2420000
0&
#2425000
b11 -
b101111 +
1&
#2430000
0&
#2435000
1'
b0 -
b110000 +
1&
#2440000
0&
#2445000
b100 4
0'
b1 -
b110001 +
1&
#2450000
0&
#2455000
b10 -
b110010 +
1&
#2460000
0&
#2465000
b11 -
b110011 +
1&
#2470000
0&
#2475000
1'
b0 -
b110100 +
1&
#2480000
0&
#2485000
b101 4
0'
b1 -
b110101 +
1&
#2490000
0&
#2495000
b10 -
b110110 +
1&
#2500000
0&
#2505000
b11 -
b110111 +
1&
#2510000
0&
#2515000
1'
b0 -
b111000 +
1&
#2520000
0&
#2525000
b110 4
0'
b1 -
b111001 +
1&
#2530000
0&
#2535000
b10 -
b111010 +
1&
#2540000
0&
#2545000
b11 -
b111011 +
1&
#2550000
0&
#2555000
1'
b0 -
b111100 +
1&
#2560000
0&
#2565000
b111 4
0'
b1 -
b111101 +
1&
#2570000
0&
#2575000
b10 -
b111110 +
1&
#2580000
0&
#2585000
b11 -
b111111 +
1&
#2590000
0&
#2595000
1'
b0 -
1%
b0 +
1&
#2600000
0&
#2605000
b11 ?
b10100 @
1!
b1000 4
0'
b1 -
0%
b1 +
1&
#2610000
0&
#2615000
b10 -
b10 +
16
1&
#2620000
0&
#2625000
1.
17
b11 -
b11 +
1&
#2630000
0&
#2635000
1'
b0 -
b100 +
1&
#2640000
0&
#2645000
b1001 4
0'
b1 -
b101 +
1&
#2650000
0&
#2655000
b10 -
b110 +
1&
#2660000
0&
#2665000
b11 -
b111 +
1&
#2670000
0&
#2675000
1'
b0 -
b1000 +
1&
#2680000
0&
#2685000
b1010 4
0'
b1 -
b1001 +
1&
#2690000
0&
#2695000
b10 -
b1010 +
1&
#2700000
0&
#2705000
b11 -
b1011 +
1&
#2710000
0&
#2715000
1'
b0 -
b1100 +
1&
#2720000
0&
#2725000
b1011 4
0'
b1 -
b1101 +
1&
#2730000
0&
#2735000
b10 -
b1110 +
1&
#2740000
0&
#2745000
b11 -
b1111 +
1&
#2750000
0&
#2755000
1'
b0 -
b10000 +
1&
#2760000
0&
#2765000
b1100 4
0'
b1 -
b10001 +
1&
#2770000
0&
#2775000
b10 -
b10010 +
1&
#2780000
0&
#2785000
b11 -
b10011 +
1&
#2790000
0&
#2795000
1'
b0 -
b10100 +
1&
#2800000
0&
#2805000
b1101 4
0'
b1 -
b10101 +
1&
#2810000
0&
#2815000
b10 -
b10110 +
1&
#2820000
0&
#2825000
b11 -
b10111 +
1&
#2830000
0&
#2835000
1'
b0 -
b11000 +
1&
#2840000
0&
#2845000
b1110 4
0'
b1 -
b11001 +
1&
#2850000
0&
#2855000
b10 -
b11010 +
1&
#2860000
0&
#2865000
b11 -
b11011 +
1&
#2870000
0&
#2875000
1'
b0 -
b11100 +
1&
#2880000
0&
#2885000
b1111 4
0'
b1 -
b11101 +
1&
#2890000
0&
#2895000
b10 -
b11110 +
1&
#2900000
0&
#2905000
b11 -
b11111 +
1&
#2910000
0&
#2915000
1'
b0 -
b100000 +
1&
#2920000
0&
#2925000
b11 3
b101xxxxx 8
b0 4
0'
b1 -
b100001 +
1&
#2930000
0&
#2935000
b10 -
b100010 +
1&
#2940000
0&
#2945000
b11 -
b100011 +
1&
#2950000
0&
#2955000
1'
b0 -
b100100 +
1&
#2960000
0&
#2965000
b1 4
0'
b1 -
b100101 +
1&
#2970000
0&
#2975000
b10 -
b100110 +
1&
#2980000
0&
#2985000
b11 -
b100111 +
1&
#2990000
0&
#2995000
1'
b0 -
b101000 +
1&
#3000000
0&
#3005000
b10 4
0'
b1 -
b101001 +
1&
#3010000
0&
#3015000
b10 -
b101010 +
1&
#3020000
0&
#3025000
b11 -
b101011 +
1&
#3030000
0&
#3035000
1'
b0 -
b101100 +
1&
#3040000
0&
#3045000
b11 4
0'
b1 -
b101101 +
1&
#3050000
0&
#3055000
b10 -
b101110 +
1&
#3060000
0&
#3065000
b11 -
b101111 +
1&
#3070000
0&
#3075000
1'
b0 -
b110000 +
1&
#3080000
0&
#3085000
b100 4
0'
b1 -
b110001 +
1&
#3090000
0&
#3095000
b10 -
b110010 +
1&
#3100000
0&
#3105000
b11 -
b110011 +
1&
#3110000
0&
#3115000
1'
b0 -
b110100 +
1&
#3120000
0&
#3125000
b101 4
0'
b1 -
b110101 +
1&
#3130000
0&
#3135000
b10 -
b110110 +
1&
#3140000
0&
#3145000
b11 -
b110111 +
1&
#3150000
0&
#3155000
1'
b0 -
b111000 +
1&
#3160000
0&
#3165000
b110 4
0'
b1 -
b111001 +
1&
#3170000
0&
#3175000
b10 -
b111010 +
1&
#3180000
0&
#3185000
b11 -
b111011 +
1&
#3190000
0&
#3195000
1'
b0 -
b111100 +
1&
#3200000
0&
#3205000
b111 4
0'
b1 -
b111101 +
1&
#3210000
0&
#3215000
b10 -
b111110 +
1&
#3220000
0&
#3225000
b11 -
b111111 +
1&
#3230000
0&
#3235000
1'
b0 -
1%
b0 +
1&
#3240000
0&
#3245000
b100 ?
b1010 @
0!
b1000 4
0'
b1 -
0%
b1 +
1&
#3250000
0&
#3255000
b10 -
b10 +
06
1&
#3260000
0&
#3265000
0.
07
b11 -
b11 +
1&
#3270000
0&
#3275000
1'
b0 -
b100 +
1&
#3280000
0&
#3285000
b1001 4
0'
b1 -
b101 +
1&
#3290000
0&
#3295000
b10 -
b110 +
1&
#3300000
0&
#3305000
b11 -
b111 +
1&
#3310000
0&
#3315000
1'
b0 -
b1000 +
1&
#3320000
0&
#3325000
b1010 4
0'
b1 -
b1001 +
1&
#3330000
0&
#3335000
b10 -
b1010 +
1&
#3340000
0&
#3345000
b11 -
b1011 +
1&
#3350000
0&
#3355000
1'
b0 -
b1100 +
1&
#3360000
0&
#3365000
b1011 4
0'
b1 -
b1101 +
1&
#3370000
0&
#3375000
b10 -
b1110 +
1&
#3380000
0&
#3385000
b11 -
b1111 +
1&
#3390000
0&
#3395000
1'
b0 -
b10000 +
1&
#3400000
0&
#3405000
b1100 4
0'
b1 -
b10001 +
1&
#3410000
0&
#3415000
b10 -
b10010 +
1&
#3420000
0&
#3425000
b11 -
b10011 +
1&
#3430000
0&
#3435000
1'
b0 -
b10100 +
1&
#3440000
0&
#3445000
b1101 4
0'
b1 -
b10101 +
1&
#3450000
0&
#3455000
b10 -
b10110 +
1&
#3460000
0&
#3465000
b11 -
b10111 +
1&
#3470000
0&
#3475000
1'
b0 -
b11000 +
1&
#3480000
0&
#3485000
b1110 4
0'
b1 -
b11001 +
1&
#3490000
0&
#3495000
b10 -
b11010 +
1&
#3500000
0&
#3505000
b11 -
b11011 +
1&
#3510000
0&
#3515000
1'
b0 -
b11100 +
1&
#3520000
0&
#3525000
b1111 4
0'
b1 -
b11101 +
1&
